[
  {
    "OBSERVACIONES": {
      "o1Refuced": false,
      "o2Min": true,
      "o3CreatedModuls": false,
      "o4Secuens": false
    },
    "TEXTO_MODULOS": {
      "INICIA": "8:31:00",
      "TERMINA": "22:45:00"
    },
    "DURACION_MODULO_BASE": 44,
    "TOTAL_MODULS": 19,
    "RECESS": [],
    "namesFiles": [
      "ANTONIO-VARAS.xlsx",
      "MAIPU.xlsx",
      "PLAZA-NORTE.xlsx",
      "PLAZA-OESTE.xlsx",
      "PLAZA-VESPUCIO.xlsx",
      "SAN-CARLOS-DE-APOQUINDO.xlsx"
    ],
    "namesFiles2": [
      "ANTONIO VARAS",
      "MAIPÚ",
      "PLAZA NORTE",
      "PLAZA OESTE",
      "PLAZA VESPUCIO",
      "SAN CARLOS DE APOQUINDO"
    ]
  },
  {
    "OBSERVACIONES": {
      "o1Refuced": false,
      "o2Min": false,
      "o3CreatedModuls": false,
      "o4Secuens": false
    },
    "TEXTO_MODULOS": {
      "INICIA": "8:31:00",
      "TERMINA": "22:45:00"
    },
    "DURACION_MODULO_BASE": 44,
    "TOTAL_MODULS": 19,
    "RECESS": [],
    "namesFiles": [
      "CONCEPCION.xlsx",
      "MELIPILLA.xlsx",
      "PADRE-ALONSO-DE-OVALLE.xlsx",
      "PUENTE-ALTO.xlsx",
      "SAN-BERNARDO.xlsx"
    ],
    "namesFiles2": [
      "CONCEPCIÓN",
      "MELIPILLA",
      "PADRE ALONSO DE OVALLE",
      "PUENTE ALTO",
      "SAN BERNARDO"
    ]
  },
  {
    "OBSERVACIONES": {
      "o1Refuced": true,
      "o2Min": false,
      "o3CreatedModuls": false,
      "o4Secuens": false
    },
    "TEXTO_MODULOS": {
      "INICIA": "7:01:00",
      "TERMINA": "22:45:00"
    },
    "DURACION_MODULO_BASE": 44,
    "TOTAL_MODULS": 21,
    "RECESS": [],
    "namesFiles": [
      "SAN-JOAQUIN.xlsx"
    ],
    "namesFiles2": [
      "SAN JOAQUÍN"
    ]
  },
  {
    "OBSERVACIONES": {
      "o1Refuced": true,
      "o2Min": false,
      "o3CreatedModuls": false,
      "o4Secuens": false
    },
    "TEXTO_MODULOS": {
      "INICIA": "8:01:00",
      "TERMINA": "23:00:00"
    },
    "DURACION_MODULO_BASE": 44,
    "TOTAL_MODULS": 20,
    "RECESS": [],
    "namesFiles": [
      "VALPARAISO.xlsx"
    ],
    "namesFiles2": [
      "VALPARAÍSO"
    ]
  },
  {
    "OBSERVACIONES": {
      "o1Refuced": false,
      "o2Min": false,
      "o3CreatedModuls": false,
      "o4Secuens": false
    },
    "TEXTO_MODULOS": {
      "INICIA": "8:01:00",
      "TERMINA": "23:45:00"
    },
    "DURACION_MODULO_BASE": 44,
    "TOTAL_MODULS": 21,
    "RECESS": [],
    "namesFiles": [
      "VINA-DEL-MAR.xlsx"
    ],
    "namesFiles2": [
      "VIÑA DEL MAR"
    ]
  }
]